napari_math/__init__.py
napari_math/_widget.py
napari_math/napari.yaml
napari_math/_tests/__init__.py
napari_math/_tests/test_widget.py
napari_math-0.0.1b0.dist-info/LICENSE
napari_math-0.0.1b0.dist-info/METADATA
napari_math-0.0.1b0.dist-info/WHEEL
napari_math-0.0.1b0.dist-info/entry_points.txt
napari_math-0.0.1b0.dist-info/top_level.txt
napari_math-0.0.1b0.dist-info/RECORD
