Metadata-Version: 2.1
Name: napari-math
Version: 0.0.1b0
Summary: Simple mathematical operations on image, point and surface layers.
Home-page: https://github.com/zacsimile/napari-math
Author: Zach Marin, Talley Lambert
Author-email: zach.marin@yale.edu
License: MIT
Project-URL: Bug Tracker, https://github.com/zacsimile/napari-math/issues
Project-URL: Documentation, https://github.com/zacsimile/napari-math#README.md
Project-URL: Source Code, https://github.com/zacsimile/napari-math
Project-URL: User Support, https://github.com/zacsimile/napari-math/issues
Platform: UNKNOWN
Classifier: Development Status :: 2 - Pre-Alpha
Classifier: Intended Audience :: Developers
Classifier: Framework :: napari
Classifier: Topic :: Software Development :: Testing
Classifier: Programming Language :: Python
Classifier: Programming Language :: Python :: 3
Classifier: Programming Language :: Python :: 3.7
Classifier: Programming Language :: Python :: 3.8
Classifier: Programming Language :: Python :: 3.9
Classifier: Programming Language :: Python :: 3.10
Classifier: Operating System :: OS Independent
Classifier: License :: OSI Approved :: MIT License
Requires-Python: >=3.7
License-File: LICENSE
Requires-Dist: numpy
